JSJumble/__init__.py
JSJumble/server.py
JSJumble/static/compress.js
JSJumble/static/obfuscator.js
JSJumble/template/obfuscator.html
JSJumble-1.0.4.dist-info/LICENSE
JSJumble-1.0.4.dist-info/METADATA
JSJumble-1.0.4.dist-info/WHEEL
JSJumble-1.0.4.dist-info/top_level.txt
JSJumble-1.0.4.dist-info/RECORD
